etrip/__init__.py
etrip/_version.py
etrip/etrip.py
etrip/imageselector.py
etrip/classes/cut.py
etrip/classes/initialisation.py
etrip/classes/manager.py
etrip/classes/manual.py
etrip/classes/sample.py
etrip/classes/selection.py
etrip-0.0.6.dist-info/licenses/LICENSE
etrip-0.0.6.dist-info/METADATA
etrip-0.0.6.dist-info/WHEEL
etrip-0.0.6.dist-info/top_level.txt
etrip-0.0.6.dist-info/RECORD
