Metadata-Version: 2.4
Name: etrip
Version: 0.0.6
Summary: Easy Tracking of Rhythms in Plants
Author-email: Matthijs Brouwer <matthijs.brouwer@wur.nl>
License: GNU GENERAL PUBLIC LICENSE
Classifier: Topic :: Scientific/Engineering :: Bio-Informatics
Classifier: Programming Language :: Python :: 3.10
Classifier: Operating System :: OS Independent
Requires-Python: >=3.12
License-File: LICENSE
Requires-Dist: ipycanvas>=0.14.1
Requires-Dist: ipyfilechooser>=0.6.0
Requires-Dist: ipywidgets>=8.1.7
Requires-Dist: jupyter_bbox_widget>=0.6.0
Requires-Dist: matplotlib>=3.10.6
Requires-Dist: numpy<2.3.0,>=2
Requires-Dist: opencv_contrib_python>=4.12.0.88
Requires-Dist: opencv_python>=4.11.0.86
Requires-Dist: pandas>=2.3.2
Requires-Dist: Pillow>=11.3.0
Requires-Dist: scipy>=1.16.2
Requires-Dist: tqdm>=4.67.1
Dynamic: license-file
